{"cameraMode":{"drawMode":0,"name":"Shaded","section":"Shading Mode"},"sceneLighting":false,"audioPlay":false,"sceneViewState":{"m_AlwaysRefresh":false,"showFog":true,"showSkybox":false,"showFlares":true,"showImageEffects":true,"showParticleSystems":true,"showVisualEffectGraphs":true,"m_FxEnabled":true},"in2DMode":false,"pivot":{"x":0.8982102870941162,"y":0.6521931290626526,"z":0.9380748271942139},"rotation":{"x":0.013421080075204373,"y":-0.9546939134597778,"z":0.2940763831138611,"w":0.04357026889920235},"size":2.052638053894043,"orthographic":false}